CarterOfflineNonPT
