Metadata-Version: 2.1
Name: Carter-Offline-NoPT
Version: 1.0.2
Home-page: https://github.com/Cipher58
Download-URL: https://github.com/Cipher58/Carter-Offline/
Author: Cipher58
Author-email: cipher58public@gmail.com
License: Lily 1.0
Classifier: Programming Language :: Python :: 3
Classifier: Operating System :: OS Independent
License-File: LICENSE
